derip2/__init__.py
derip2/_version.py
derip2/aln_ops.py
derip2/app.py
derip2/derip.py
derip2/plotting/minialign.py
derip2/utils/checks.py
derip2/utils/logs.py
derip2-0.4.1.dist-info/METADATA
derip2-0.4.1.dist-info/WHEEL
derip2-0.4.1.dist-info/entry_points.txt
derip2-0.4.1.dist-info/licenses/LICENSE
derip2-0.4.1.dist-info/RECORD
