Metadata-Version: 2.4
Name: derip2
Version: 0.4.1
Summary: Predict ancestral sequence of fungal repeat elements by correcting for RIP-like mutations in multi-sequence DNA alignments.
Project-URL: homepage, https://github.com/adamtaranto/derip2
Project-URL: documentation, https://github.com/adamtaranto/derip2
Project-URL: repository, https://github.com/adamtaranto/derip2
Author: Adam Taranto
License: MIT
License-File: LICENSE
Classifier: Intended Audience :: Science/Research
Classifier: License :: OSI Approved :: MIT License
Classifier: Programming Language :: Python :: 3
Classifier: Topic :: Scientific/Engineering :: Bio-Informatics
Requires-Python: >=3.8
Requires-Dist: biopython>1.80
Requires-Dist: click
Requires-Dist: matplotlib
Requires-Dist: numpy
Requires-Dist: pandas
Requires-Dist: tqdm
Provides-Extra: dev
Requires-Dist: hatch; extra == 'dev'
Requires-Dist: isort; extra == 'dev'
Requires-Dist: mkdocs; extra == 'dev'
Requires-Dist: mkdocs-jupyter; extra == 'dev'
Requires-Dist: mkdocs-material; extra == 'dev'
Requires-Dist: mkdocstrings; extra == 'dev'
Requires-Dist: mkdocstrings-python; extra == 'dev'
Requires-Dist: notebook; extra == 'dev'
Requires-Dist: numpydoc-validation; extra == 'dev'
Requires-Dist: pre-commit; extra == 'dev'
Requires-Dist: pymdown-extensions; extra == 'dev'
Requires-Dist: pytest; extra == 'dev'
Requires-Dist: pytest-cov; extra == 'dev'
Requires-Dist: ruff; extra == 'dev'
Requires-Dist: seaborn; extra == 'dev'
